emergent_pytorch/__init__.py
emergent_pytorch/emergent.py
emergent_pytorch/utils.py
emergent_pytorch/units/__init__.py
emergent_pytorch/units/mixer.py
emergent_pytorch-0.0.1.dist-info/LICENSE
emergent_pytorch-0.0.1.dist-info/METADATA
emergent_pytorch-0.0.1.dist-info/WHEEL
emergent_pytorch-0.0.1.dist-info/top_level.txt
emergent_pytorch-0.0.1.dist-info/RECORD
