Metadata-Version: 2.1
Name: emergent-pytorch
Version: 0.0.1
Summary: Emergent - Pytorch
Home-page: https://github.com/archinetai/emergent-pytorch
Author: Flavio Schneider
Author-email: archinetai@protonmail.com
License: MIT
Keywords: artificial intelligence,deep learning,distributed learning
Classifier: Development Status :: 4 - Beta
Classifier: Intended Audience :: Developers
Classifier: Topic :: Scientific/Engineering :: Artificial Intelligence
Classifier: License :: OSI Approved :: MIT License
Classifier: Programming Language :: Python :: 3.6
License-File: LICENSE
Requires-Dist: torch (>=1.6)
Requires-Dist: data-science-types (>=0.2)
